slg_test_7/__init__.py
slg_test_7/importable.py
slg_test_7-1.0.3.data/scripts/slg-test-7
slg_test_7-1.0.3.dist-info/METADATA
slg_test_7-1.0.3.dist-info/WHEEL
slg_test_7-1.0.3.dist-info/top_level.txt
slg_test_7-1.0.3.dist-info/RECORD
