Metadata-Version: 2.1
Name: slg-test-7
Version: 1.0.3
Summary: This is a description.
Home-page: UNKNOWN
License: UNKNOWN
Platform: UNKNOWN
Requires-Python: >=3.6.3
Requires-Dist: colored (==1.3.93)
